{
  "id": "76bb5159-5419-4d6f-80f8-63176c6478cc",
  "prevId": "00000000-0000-0000-0000-000000000000",
  "version": "7",
  "dialect": "postgresql",
  "tables": {
    "public.DeletionLog": {
      "name": "DeletionLog",
      "schema": "",
      "columns": {
        "id": {
          "name": "id",
          "type": "uuid",
          "primaryKey": true,
          "notNull": true,
          "default": "gen_random_uuid()"
        },
        "userId": {
          "name": "userId",
          "type": "text",
          "primaryKey": false,
          "notNull": true
        },
        "userType": {
          "name": "userType",
          "type": "text",
          "primaryKey": false,
          "notNull": true
        },
        "mediaCount": {
          "name": "mediaCount",
          "type": "integer",
          "primaryKey": false,
          "notNull": true
        },
        "deletedBy": {
          "name": "deletedBy",
          "type": "text",
          "primaryKey": false,
          "notNull": true
        },
        "reason": {
          "name": "reason",
          "type": "text",
          "primaryKey": false,
          "notNull": false
        },
        "createdAt": {
          "name": "createdAt",
          "type": "timestamp",
          "primaryKey": false,
          "notNull": true,
          "default": "now()"
        }
      },
      "indexes": {},
      "foreignKeys": {},
      "compositePrimaryKeys": {},
      "uniqueConstraints": {},
      "policies": {},
      "checkConstraints": {},
      "isRLSEnabled": false
    },
    "public.Media": {
      "name": "Media",
      "schema": "",
      "columns": {
        "id": {
          "name": "id",
          "type": "uuid",
          "primaryKey": true,
          "notNull": true,
          "default": "gen_random_uuid()"
        },
        "key": {
          "name": "key",
          "type": "text",
          "primaryKey": false,
          "notNull": true
        },
        "url": {
          "name": "url",
          "type": "text",
          "primaryKey": false,
          "notNull": true
        },
        "type": {
          "name": "type",
          "type": "text",
          "primaryKey": false,
          "notNull": true
        },
        "size": {
          "name": "size",
          "type": "integer",
          "primaryKey": false,
          "notNull": true
        },
        "ownerId": {
          "name": "ownerId",
          "type": "text",
          "primaryKey": false,
          "notNull": true
        },
        "ownerType": {
          "name": "ownerType",
          "type": "text",
          "primaryKey": false,
          "notNull": true
        },
        "app": {
          "name": "app",
          "type": "text",
          "primaryKey": false,
          "notNull": true
        },
        "metadata": {
          "name": "metadata",
          "type": "jsonb",
          "primaryKey": false,
          "notNull": false
        },
        "createdAt": {
          "name": "createdAt",
          "type": "timestamp",
          "primaryKey": false,
          "notNull": true,
          "default": "now()"
        },
        "updatedAt": {
          "name": "updatedAt",
          "type": "timestamp",
          "primaryKey": false,
          "notNull": true,
          "default": "now()"
        },
        "deletedAt": {
          "name": "deletedAt",
          "type": "timestamp",
          "primaryKey": false,
          "notNull": false
        }
      },
      "indexes": {
        "Media_ownerId_ownerType_idx": {
          "name": "Media_ownerId_ownerType_idx",
          "columns": [
            {
              "expression": "ownerId",
              "isExpression": false,
              "asc": true,
              "nulls": "last"
            },
            {
              "expression": "ownerType",
              "isExpression": false,
              "asc": true,
              "nulls": "last"
            }
          ],
          "isUnique": false,
          "concurrently": false,
          "method": "btree",
          "with": {}
        },
        "Media_app_idx": {
          "name": "Media_app_idx",
          "columns": [
            {
              "expression": "app",
              "isExpression": false,
              "asc": true,
              "nulls": "last"
            }
          ],
          "isUnique": false,
          "concurrently": false,
          "method": "btree",
          "with": {}
        },
        "Media_createdAt_idx": {
          "name": "Media_createdAt_idx",
          "columns": [
            {
              "expression": "createdAt",
              "isExpression": false,
              "asc": true,
              "nulls": "last"
            }
          ],
          "isUnique": false,
          "concurrently": false,
          "method": "btree",
          "with": {}
        }
      },
      "foreignKeys": {},
      "compositePrimaryKeys": {},
      "uniqueConstraints": {
        "Media_key_unique": {
          "name": "Media_key_unique",
          "nullsNotDistinct": false,
          "columns": [
            "key"
          ]
        }
      },
      "policies": {},
      "checkConstraints": {},
      "isRLSEnabled": false
    }
  },
  "enums": {},
  "schemas": {},
  "sequences": {},
  "roles": {},
  "policies": {},
  "views": {},
  "_meta": {
    "columns": {},
    "schemas": {},
    "tables": {}
  }
}